experiments/__init__.py
experiments/admin_urls.py
experiments/models.py
experiments/utils.py
experiments/views.py
experiments/wagtail_hooks.py
experiments/backends/__init__.py
experiments/backends/db.py
experiments/management/__init__.py
experiments/management/commands/__init__.py
experiments/management/commands/experiment-data.py
experiments/migrations/0001_initial.py
experiments/migrations/0002_experiment_history.py
experiments/migrations/0003_experiment_status.py
experiments/migrations/0004_add_completed_status.py
experiments/migrations/0005_make_goal_optional.py
experiments/migrations/0006_downcase_verbose_names.py
experiments/migrations/0007_alternative_revision.py
experiments/migrations/__init__.py
experiments/static/experiments/css/vendor/c3-v0.4.11.min.css
experiments/static/experiments/js/vendor/c3-v0.4.11.min.js
experiments/static/experiments/js/vendor/d3-v3.5.17.min.js
experiments/templates/experiments/report.html
tests/__init__.py
tests/models.py
tests/settings.py
tests/tests.py
tests/urls.py
tests/migrations/0001_initial.py
tests/migrations/0002_simplepagerelatedlink.py
tests/migrations/__init__.py
wagtail_experiments-0.4.dist-info/LICENSE
wagtail_experiments-0.4.dist-info/METADATA
wagtail_experiments-0.4.dist-info/WHEEL
wagtail_experiments-0.4.dist-info/top_level.txt
wagtail_experiments-0.4.dist-info/RECORD
